linecheck/__init__.py
linecheck/main.py
linecheck-0.1.0.dist-info/METADATA
linecheck-0.1.0.dist-info/WHEEL
linecheck-0.1.0.dist-info/entry_points.txt
linecheck-0.1.0.dist-info/top_level.txt
linecheck-0.1.0.dist-info/RECORD
